[
{
  "model": "auth.user",
  "pk": 1,
  "fields": {
    "password": "!LNolRz2SiW8kZuclUuuJ9pYiETVRmAASvzMNOwWZ",
    "last_login": "2025-10-20T21:11:27.608Z",
    "is_superuser": false,
    "username": "Dev1s0n",
    "first_name": "",
    "last_name": "",
    "email": "",
    "is_staff": false,
    "is_active": true,
    "date_joined": "2025-10-20T21:11:26.517Z",
    "groups": [],
    "user_permissions": []
  }
},
{
  "model": "auth.user",
  "pk": 2,
  "fields": {
    "password": "pbkdf2_sha256$870000$T36Pm2I0W985aYysAu36RM$cgTMYi0GxK3QybEWAVuFbtF70/T+1NdIhrtkZ5U6j1M=",
    "last_login": null,
    "is_superuser": true,
    "username": "Dev1s0n1",
    "first_name": "",
    "last_name": "",
    "email": "tfreedfreed@gmail.com",
    "is_staff": true,
    "is_active": true,
    "date_joined": "2025-10-21T00:00:51.785Z",
    "groups": [],
    "user_permissions": []
  }
}
]
